{"domain": [{"type": "CategoricalVariable", "is_objective": false, "name": "inputs[\"Catalyst\"].components[0].identifiers[0].value", "description": "Catalyst", "units": null, "levels": ["cycloPd tBuXPhos 4-Chlorotoluene", "cycloPd EPhos 4-Chlorotoluene", "cycloPd AlPhos 4-Chlorotoluene", "cycloPd tBuBrettPhos 4-Chlorotoluene"], "ds": null}, {"type": "CategoricalVariable", "is_objective": false, "name": "inputs[\"Base\"].components[0].identifiers[0].value", "description": "Base", "units": null, "levels": ["TEA", "Triethylamine", "TMG", "BTMG", "DBU", "MTBD", "BTTP", "P2Et"], "ds": null}, {"type": "CategoricalVariable", "is_objective": false, "name": "inputs[\"Solvent\"].components[0].identifiers[0].value", "description": "Solvent", "units": null, "levels": ["2-MeTHF", "DMSO"], "ds": null}, {"type": "ContinuousVariable", "is_objective": false, "name": "outcomes[0].reaction_time.value", "description": "Residence time in seconds (s)", "units": null, "bounds": [60.0, 6000.0]}, {"type": "ContinuousVariable", "is_objective": false, "name": "conditions.temperature.setpoint.value", "description": "Reactor temperature in degrees Celsius (\u00baC)", "units": null, "bounds": [30.0, 110.0]}, {"type": "ContinuousVariable", "is_objective": true, "name": "outcomes[0].products[0].measurements[0].percentage.value", "description": "Yield", "units": null, "bounds": [0.0, 105.0]}], "name": "ExperimentalEmulator", "data": {"index": [0], "columns": [["inputs[\"Catalyst\"].components[0].identifiers[0].value", "DATA"], ["inputs[\"Base\"].components[0].identifiers[0].value", "DATA"], ["inputs[\"Solvent\"].components[0].identifiers[0].value", "DATA"], ["outcomes[0].reaction_time.value", "DATA"], ["conditions.temperature.setpoint.value", "DATA"], ["outcomes[0].products[0].measurements[0].percentage.value", "DATA"], ["computation_t", "METADATA"], ["experiment_t", "METADATA"], ["strategy", "METADATA"]], "data": [["cycloPd EPhos 4-Chlorotoluene", "BTMG", "2-MeTHF", 1324, 65.0, 59.232276916503906, 0.0, 0.029716968536376953, NaN]]}, "experiment_params": {"model_name": "morpholine_bm", "regressor_name": "ANNRegressor", "n_features": 16, "n_examples": 131, "descriptors_features": [], "output_variable_names": ["outcomes[0].products[0].measurements[0].percentage.value"], "predictors": [{"input_preprocessor": {"num": {"mean_": [642.4078620992681, 74.12043003369403], "var_": [259178.35855442128, 864.4022702640142], "scale_": [509.09562810381834, 29.400718873252302], "n_samples_seen_": 93}}, "output_preprocessor": {"mean_": [54.014445674355315], "var_": [1746.7694298650629], "scale_": [41.79437079159181], "n_samples_seen_": 93}}, {"input_preprocessor": {"num": {"mean_": [689.4838050924321, 74.13440856113229], "var_": [254634.09526866654, 891.4515053156904], "scale_": [504.6128171862726, 29.857185153923844], "n_samples_seen_": 93}}, "output_preprocessor": {"mean_": [49.86996207258073], "var_": [1739.0440074500218], "scale_": [41.70184657122538], "n_samples_seen_": 93}}, {"input_preprocessor": {"num": {"mean_": [673.7668703769116, 71.29468077801644], "var_": [253345.13771982936, 929.8196516316743], "scale_": [503.3340220170194, 30.492944292601106], "n_samples_seen_": 94}}, "output_preprocessor": {"mean_": [49.420188527554274], "var_": [1766.8416280087004], "scale_": [42.03381529208002], "n_samples_seen_": 94}}, {"input_preprocessor": {"num": {"mean_": [694.0332223608139, 76.13936160473114], "var_": [253445.37866599104, 858.3713234200567], "scale_": [503.43358913166594, 29.297974732395012], "n_samples_seen_": 94}}, "output_preprocessor": {"mean_": [53.48275846345945], "var_": [1809.0774003520926], "scale_": [42.533250526524455], "n_samples_seen_": 94}}, {"input_preprocessor": {"num": {"mean_": [700.069684211244, 75.45425524610154], "var_": [257683.72181477072, 853.0097154216675], "scale_": [507.6255724594366, 29.20633005739796], "n_samples_seen_": 94}}, "output_preprocessor": {"mean_": [53.16249431867866], "var_": [1782.740902357913], "scale_": [42.22251653274486], "n_samples_seen_": 94}}], "clip": true}, "extras": [{}, {}]}