{"runner": {"num_initial_experiments": null, "max_iterations": 20, "batch_size": 1, "f_tol": 1e-05, "max_restarts": 0}, "strategy": {"name": "MTBO", "transform": {"transform_domain": [{"type": "CategoricalVariable", "is_objective": false, "name": "inputs[\"Catalyst\"].components[0].identifiers[0].value", "description": "Catalyst", "units": null, "levels": ["cycloPd tBuXPhos 4-Chlorotoluene", "cycloPd EPhos 4-Chlorotoluene", "cycloPd AlPhos 4-Chlorotoluene", "cycloPd tBuBrettPhos 4-Chlorotoluene"], "ds": null}, {"type": "CategoricalVariable", "is_objective": false, "name": "inputs[\"Base\"].components[0].identifiers[0].value", "description": "Base", "units": null, "levels": ["TEA", "Triethylamine", "TMG", "BTMG", "DBU", "MTBD", "BTTP", "P2Et"], "ds": null}, {"type": "CategoricalVariable", "is_objective": false, "name": "inputs[\"Solvent\"].components[0].identifiers[0].value", "description": "Solvent", "units": null, "levels": ["2-MeTHF", "DMSO"], "ds": null}, {"type": "ContinuousVariable", "is_objective": false, "name": "outcomes[0].reaction_time.value", "description": "Residence time in seconds (s)", "units": null, "bounds": [60.0, 6000.0]}, {"type": "ContinuousVariable", "is_objective": false, "name": "conditions.temperature.setpoint.value", "description": "Reactor temperature in degrees Celsius (\u00baC)", "units": null, "bounds": [30.0, 110.0]}, {"type": "ContinuousVariable", "is_objective": true, "name": "outcomes[0].products[0].measurements[0].percentage.value", "description": "Residence time in seconds (s)", "units": null, "bounds": [0.0, 105.0]}], "name": "Transform", "domain": [{"type": "CategoricalVariable", "is_objective": false, "name": "inputs[\"Catalyst\"].components[0].identifiers[0].value", "description": "Catalyst", "units": null, "levels": ["cycloPd tBuXPhos 4-Chlorotoluene", "cycloPd EPhos 4-Chlorotoluene", "cycloPd AlPhos 4-Chlorotoluene", "cycloPd tBuBrettPhos 4-Chlorotoluene"], "ds": null}, {"type": "CategoricalVariable", "is_objective": false, "name": "inputs[\"Base\"].components[0].identifiers[0].value", "description": "Base", "units": null, "levels": ["TEA", "Triethylamine", "TMG", "BTMG", "DBU", "MTBD", "BTTP", "P2Et"], "ds": null}, {"type": "CategoricalVariable", "is_objective": false, "name": "inputs[\"Solvent\"].components[0].identifiers[0].value", "description": "Solvent", "units": null, "levels": ["2-MeTHF", "DMSO"], "ds": null}, {"type": "ContinuousVariable", "is_objective": false, "name": "outcomes[0].reaction_time.value", "description": "Residence time in seconds (s)", "units": null, "bounds": [60.0, 6000.0]}, {"type": "ContinuousVariable", "is_objective": false, "name": "conditions.temperature.setpoint.value", "description": "Reactor temperature in degrees Celsius (\u00baC)", "units": null, "bounds": [30.0, 110.0]}, {"type": "ContinuousVariable", "is_objective": true, "name": "outcomes[0].products[0].measurements[0].percentage.value", "description": "Residence time in seconds (s)", "units": null, "bounds": [0.0, 105.0]}], "transform_params": {}}, "strategy_params": {"all_experiments": {"index": [0, 1, 0, 0, 0, 0, 0, 0, 0, 0, 0, 0, 0, 0, 0, 0, 0, 0, 0, 0], "columns": [["inputs[\"Catalyst\"].components[0].identifiers[0].value", "DATA"], ["inputs[\"Base\"].components[0].identifiers[0].value", "DATA"], ["inputs[\"Solvent\"].components[0].identifiers[0].value", "DATA"], ["outcomes[0].reaction_time.value", "DATA"], ["conditions.temperature.setpoint.value", "DATA"], ["outcomes[0].products[0].measurements[0].percentage.value", "DATA"], ["computation_t", "METADATA"], ["experiment_t", "METADATA"], ["strategy", "METADATA"], ["task", "METADATA"]], "data": [["cycloPd AlPhos 4-Chlorotoluene", "TMG", "DMSO", 1545.0, 50.0, 43.63129425048828, 0.0, 0.023556947708129883, "LHS", 1.0], ["cycloPd EPhos 4-Chlorotoluene", "Triethylamine", "DMSO", 4515.0, 90.0, 49.89719772338867, 0.0, 0.02177262306213379, "LHS", 1.0], ["cycloPd EPhos 4-Chlorotoluene", "Triethylamine", "DMSO", 4586.52099609375, 97.05900573730469, 54.10291290283203, 0.7085051536560059, 0.01871633529663086, "MTBO", 1.0], ["cycloPd tBuBrettPhos 4-Chlorotoluene", "BTTP", "2-MeTHF", 587.2060546875, 85.44536590576172, 66.94877624511719, 0.6992568969726562, 0.01872992515563965, "MTBO", 1.0], ["cycloPd tBuBrettPhos 4-Chlorotoluene", "BTMG", "2-MeTHF", 1445.8714599609375, 91.93546295166016, 105.0, 0.9499690532684326, 0.019111156463623047, "MTBO", 1.0], ["cycloPd tBuBrettPhos 4-Chlorotoluene", "BTTP", "2-MeTHF", 60.0, 106.09650421142578, 73.06193542480469, 0.6387159824371338, 0.020030975341796875, "MTBO", 1.0], ["cycloPd tBuBrettPhos 4-Chlorotoluene", "BTMG", "2-MeTHF", 1675.530029296875, 96.16236877441406, 105.0, 1.2135019302368164, 0.019207000732421875, "MTBO", 1.0], ["cycloPd tBuBrettPhos 4-Chlorotoluene", "BTTP", "2-MeTHF", 1247.9091796875, 108.9821548461914, 89.61003112792969, 0.8997859954833984, 0.019076108932495117, "MTBO", 1.0], ["cycloPd tBuBrettPhos 4-Chlorotoluene", "BTMG", "2-MeTHF", 1783.343994140625, 89.236572265625, 104.2516098022461, 0.759429931640625, 0.019237995147705078, "MTBO", 1.0], ["cycloPd tBuBrettPhos 4-Chlorotoluene", "BTMG", "2-MeTHF", 1622.3184814453125, 92.43083190917969, 105.0, 0.9135799407958984, 0.019544124603271484, "MTBO", 1.0], ["cycloPd AlPhos 4-Chlorotoluene", "BTTP", "2-MeTHF", 1175.71533203125, 57.17491149902344, 54.46660614013672, 0.6900999546051025, 0.018886804580688477, "MTBO", 1.0], ["cycloPd tBuBrettPhos 4-Chlorotoluene", "BTTP", "2-MeTHF", 1954.548095703125, 96.5094985961914, 83.05712890625, 0.6556131839752197, 0.019095182418823242, "MTBO", 1.0], ["cycloPd tBuBrettPhos 4-Chlorotoluene", "BTMG", "2-MeTHF", 1531.998046875, 79.43616485595703, 102.36864471435547, 1.092055082321167, 0.019019126892089844, "MTBO", 1.0], ["cycloPd tBuBrettPhos 4-Chlorotoluene", "BTMG", "2-MeTHF", 1463.76318359375, 107.40272521972656, 105.0, 0.8152329921722412, 0.019965171813964844, "MTBO", 1.0], ["cycloPd tBuBrettPhos 4-Chlorotoluene", "BTMG", "2-MeTHF", 2201.991455078125, 71.23518371582031, 96.4571304321289, 0.6041979789733887, 0.019131898880004883, "MTBO", 1.0], ["cycloPd tBuBrettPhos 4-Chlorotoluene", "P2Et", "2-MeTHF", 1185.7884521484375, 88.53517150878906, 75.7028579711914, 0.5435268878936768, 0.01982903480529785, "MTBO", 1.0], ["cycloPd tBuBrettPhos 4-Chlorotoluene", "P2Et", "2-MeTHF", 2918.66845703125, 110.0, 93.96076965332031, 0.7414999008178711, 0.01959395408630371, "MTBO", 1.0], ["cycloPd tBuBrettPhos 4-Chlorotoluene", "BTMG", "2-MeTHF", 1423.2491455078125, 47.123878479003906, 86.21036529541016, 0.74434494972229, 0.019538164138793945, "MTBO", 1.0], ["cycloPd tBuBrettPhos 4-Chlorotoluene", "P2Et", "2-MeTHF", 3310.4189453125, 83.17672729492188, 78.34771728515625, 0.8633379936218262, 0.019683837890625, "MTBO", 1.0], ["cycloPd tBuBrettPhos 4-Chlorotoluene", "BTTP", "2-MeTHF", 3633.026123046875, 110.0, 96.9203872680664, 0.6187520027160645, 0.019555091857910156, "MTBO", 1.0]]}, "categorical_method": "one-hot", "task": 1}}, "experiment": {"domain": [{"type": "CategoricalVariable", "is_objective": false, "name": "inputs[\"Catalyst\"].components[0].identifiers[0].value", "description": "Catalyst", "units": null, "levels": ["cycloPd tBuXPhos 4-Chlorotoluene", "cycloPd EPhos 4-Chlorotoluene", "cycloPd AlPhos 4-Chlorotoluene", "cycloPd tBuBrettPhos 4-Chlorotoluene"], "ds": null}, {"type": "CategoricalVariable", "is_objective": false, "name": "inputs[\"Base\"].components[0].identifiers[0].value", "description": "Base", "units": null, "levels": ["TEA", "Triethylamine", "TMG", "BTMG", "DBU", "MTBD", "BTTP", "P2Et"], "ds": null}, {"type": "CategoricalVariable", "is_objective": false, "name": "inputs[\"Solvent\"].components[0].identifiers[0].value", "description": "Solvent", "units": null, "levels": ["2-MeTHF", "DMSO"], "ds": null}, {"type": "ContinuousVariable", "is_objective": false, "name": "outcomes[0].reaction_time.value", "description": "Residence time in seconds (s)", "units": null, "bounds": [60.0, 6000.0]}, {"type": "ContinuousVariable", "is_objective": false, "name": "conditions.temperature.setpoint.value", "description": "Reactor temperature in degrees Celsius (\u00baC)", "units": null, "bounds": [30.0, 110.0]}, {"type": "ContinuousVariable", "is_objective": true, "name": "outcomes[0].products[0].measurements[0].percentage.value", "description": "Residence time in seconds (s)", "units": null, "bounds": [0.0, 105.0]}], "name": "ExperimentalEmulator", "data": {"index": [0, 1, 2, 3, 4, 5, 6, 7, 8, 9, 10, 11, 12, 13, 14, 15, 16, 17, 18, 19, 20], "columns": [["inputs[\"Catalyst\"].components[0].identifiers[0].value", "DATA"], ["inputs[\"Base\"].components[0].identifiers[0].value", "DATA"], ["inputs[\"Solvent\"].components[0].identifiers[0].value", "DATA"], ["outcomes[0].reaction_time.value", "DATA"], ["conditions.temperature.setpoint.value", "DATA"], ["outcomes[0].products[0].measurements[0].percentage.value", "DATA"], ["computation_t", "METADATA"], ["experiment_t", "METADATA"], ["strategy", "METADATA"], ["task", "METADATA"]], "data": [["cycloPd AlPhos 4-Chlorotoluene", "TMG", "DMSO", 1545.0, 50.0, 43.63129425048828, 0.0, 0.023556947708129883, "LHS", 1.0], ["cycloPd EPhos 4-Chlorotoluene", "Triethylamine", "DMSO", 4515.0, 90.0, 49.89719772338867, 0.0, 0.02177262306213379, "LHS", 1.0], ["cycloPd EPhos 4-Chlorotoluene", "Triethylamine", "DMSO", 4586.52099609375, 97.05900573730469, 54.10291290283203, 0.7085051536560059, 0.01871633529663086, "MTBO", 1.0], ["cycloPd tBuBrettPhos 4-Chlorotoluene", "BTTP", "2-MeTHF", 587.2060546875, 85.44536590576172, 66.94877624511719, 0.6992568969726562, 0.01872992515563965, "MTBO", 1.0], ["cycloPd tBuBrettPhos 4-Chlorotoluene", "BTMG", "2-MeTHF", 1445.8714599609375, 91.93546295166016, 105.0, 0.9499690532684326, 0.019111156463623047, "MTBO", 1.0], ["cycloPd tBuBrettPhos 4-Chlorotoluene", "BTTP", "2-MeTHF", 60.0, 106.09650421142578, 73.06193542480469, 0.6387159824371338, 0.020030975341796875, "MTBO", 1.0], ["cycloPd tBuBrettPhos 4-Chlorotoluene", "BTMG", "2-MeTHF", 1675.530029296875, 96.16236877441406, 105.0, 1.2135019302368164, 0.019207000732421875, "MTBO", 1.0], ["cycloPd tBuBrettPhos 4-Chlorotoluene", "BTTP", "2-MeTHF", 1247.9091796875, 108.9821548461914, 89.61003112792969, 0.8997859954833984, 0.019076108932495117, "MTBO", 1.0], ["cycloPd tBuBrettPhos 4-Chlorotoluene", "BTMG", "2-MeTHF", 1783.343994140625, 89.236572265625, 104.2516098022461, 0.759429931640625, 0.019237995147705078, "MTBO", 1.0], ["cycloPd tBuBrettPhos 4-Chlorotoluene", "BTMG", "2-MeTHF", 1622.3184814453125, 92.43083190917969, 105.0, 0.9135799407958984, 0.019544124603271484, "MTBO", 1.0], ["cycloPd AlPhos 4-Chlorotoluene", "BTTP", "2-MeTHF", 1175.71533203125, 57.17491149902344, 54.46660614013672, 0.6900999546051025, 0.018886804580688477, "MTBO", 1.0], ["cycloPd tBuBrettPhos 4-Chlorotoluene", "BTTP", "2-MeTHF", 1954.548095703125, 96.5094985961914, 83.05712890625, 0.6556131839752197, 0.019095182418823242, "MTBO", 1.0], ["cycloPd tBuBrettPhos 4-Chlorotoluene", "BTMG", "2-MeTHF", 1531.998046875, 79.43616485595703, 102.36864471435547, 1.092055082321167, 0.019019126892089844, "MTBO", 1.0], ["cycloPd tBuBrettPhos 4-Chlorotoluene", "BTMG", "2-MeTHF", 1463.76318359375, 107.40272521972656, 105.0, 0.8152329921722412, 0.019965171813964844, "MTBO", 1.0], ["cycloPd tBuBrettPhos 4-Chlorotoluene", "BTMG", "2-MeTHF", 2201.991455078125, 71.23518371582031, 96.4571304321289, 0.6041979789733887, 0.019131898880004883, "MTBO", 1.0], ["cycloPd tBuBrettPhos 4-Chlorotoluene", "P2Et", "2-MeTHF", 1185.7884521484375, 88.53517150878906, 75.7028579711914, 0.5435268878936768, 0.01982903480529785, "MTBO", 1.0], ["cycloPd tBuBrettPhos 4-Chlorotoluene", "P2Et", "2-MeTHF", 2918.66845703125, 110.0, 93.96076965332031, 0.7414999008178711, 0.01959395408630371, "MTBO", 1.0], ["cycloPd tBuBrettPhos 4-Chlorotoluene", "BTMG", "2-MeTHF", 1423.2491455078125, 47.123878479003906, 86.21036529541016, 0.74434494972229, 0.019538164138793945, "MTBO", 1.0], ["cycloPd tBuBrettPhos 4-Chlorotoluene", "P2Et", "2-MeTHF", 3310.4189453125, 83.17672729492188, 78.34771728515625, 0.8633379936218262, 0.019683837890625, "MTBO", 1.0], ["cycloPd tBuBrettPhos 4-Chlorotoluene", "BTTP", "2-MeTHF", 3633.026123046875, 110.0, 96.9203872680664, 0.6187520027160645, 0.019555091857910156, "MTBO", 1.0], ["cycloPd tBuBrettPhos 4-Chlorotoluene", "BTMG", "2-MeTHF", 1974.9852294921875, 110.0, 105.0, 0.8329987525939941, 0.01910996437072754, "MTBO", 1.0]]}, "experiment_params": {"model_name": "aniline_bm", "regressor_name": "ANNRegressor", "n_features": 16, "n_examples": 131, "descriptors_features": [], "output_variable_names": ["outcomes[0].products[0].measurements[0].percentage.value"], "predictors": [{"input_preprocessor": {"num": {"mean_": [665.2202986850533, 73.06021495531964], "var_": [246412.390877011, 911.5886320333475], "scale_": [496.39942674927715, 30.19252609559769], "n_samples_seen_": 93}}, "output_preprocessor": {"mean_": [53.43745720514687], "var_": [1721.5473718438097], "scale_": [41.491533736942166], "n_samples_seen_": 93}}, {"input_preprocessor": {"num": {"mean_": [700.034278705556, 73.12043003369403], "var_": [263244.11605336645, 910.0001193818263], "scale_": [513.0732073041492, 30.16620823673115], "n_samples_seen_": 93}}, "output_preprocessor": {"mean_": [53.81205248800657], "var_": [1784.7767156913717], "scale_": [42.246617801800085], "n_samples_seen_": 93}}, {"input_preprocessor": {"num": {"mean_": [674.6180766491179, 76.27765951765345], "var_": [237685.07571271728, 894.9872662369576], "scale_": [487.5295639371189, 29.916337781168295], "n_samples_seen_": 94}}, "output_preprocessor": {"mean_": [51.725438144612816], "var_": [1739.1714655452586], "scale_": [41.70337475007579], "n_samples_seen_": 94}}, {"input_preprocessor": {"num": {"mean_": [724.6279404011178, 75.19787228361089], "var_": [247220.8657068562, 889.2404225679521], "scale_": [497.213098889054, 29.820134516261863], "n_samples_seen_": 94}}, "output_preprocessor": {"mean_": [51.90500072754444], "var_": [1745.7982535768062], "scale_": [41.7827506703042], "n_samples_seen_": 94}}, {"input_preprocessor": {"num": {"mean_": [664.3423504119223, 69.74148928865473], "var_": [250764.2693916456, 989.9556179054404], "scale_": [500.7636861750716, 31.46356015941998], "n_samples_seen_": 94}}, "output_preprocessor": {"mean_": [50.111385587682115], "var_": [1794.9736570119858], "scale_": [42.36712944031004], "n_samples_seen_": 94}}], "clip": true}, "extras": [{}, {}, {}, {}, {}, {}, {}, {}, {}, {}, {}, {}, {}, {}, {}, {}, {}, {}, {}, {}, {}, {}, {}, {}, {}, {}, {}, {}, {}, {}, {}, {}, {}, {}, {}, {}, {}, {}, {}, {}, {}, {}]}}