{"runner": {"num_initial_experiments": null, "max_iterations": 20, "batch_size": 1, "f_tol": 1e-05, "max_restarts": 0}, "strategy": {"name": "MTBO", "transform": {"transform_domain": [{"type": "CategoricalVariable", "is_objective": false, "name": "inputs[\"Catalyst\"].components[0].identifiers[0].value", "description": "Catalyst", "units": null, "levels": ["cycloPd tBuXPhos 4-Chlorotoluene", "cycloPd EPhos 4-Chlorotoluene", "cycloPd AlPhos 4-Chlorotoluene", "cycloPd tBuBrettPhos 4-Chlorotoluene"], "ds": null}, {"type": "CategoricalVariable", "is_objective": false, "name": "inputs[\"Base\"].components[0].identifiers[0].value", "description": "Base", "units": null, "levels": ["TEA", "Triethylamine", "TMG", "BTMG", "DBU", "MTBD", "BTTP", "P2Et"], "ds": null}, {"type": "CategoricalVariable", "is_objective": false, "name": "inputs[\"Solvent\"].components[0].identifiers[0].value", "description": "Solvent", "units": null, "levels": ["2-MeTHF", "DMSO"], "ds": null}, {"type": "ContinuousVariable", "is_objective": false, "name": "outcomes[0].reaction_time.value", "description": "Residence time in seconds (s)", "units": null, "bounds": [60.0, 6000.0]}, {"type": "ContinuousVariable", "is_objective": false, "name": "conditions.temperature.setpoint.value", "description": "Reactor temperature in degrees Celsius (\u00baC)", "units": null, "bounds": [30.0, 110.0]}, {"type": "ContinuousVariable", "is_objective": true, "name": "outcomes[0].products[0].measurements[0].percentage.value", "description": "Residence time in seconds (s)", "units": null, "bounds": [0.0, 105.0]}], "name": "Transform", "domain": [{"type": "CategoricalVariable", "is_objective": false, "name": "inputs[\"Catalyst\"].components[0].identifiers[0].value", "description": "Catalyst", "units": null, "levels": ["cycloPd tBuXPhos 4-Chlorotoluene", "cycloPd EPhos 4-Chlorotoluene", "cycloPd AlPhos 4-Chlorotoluene", "cycloPd tBuBrettPhos 4-Chlorotoluene"], "ds": null}, {"type": "CategoricalVariable", "is_objective": false, "name": "inputs[\"Base\"].components[0].identifiers[0].value", "description": "Base", "units": null, "levels": ["TEA", "Triethylamine", "TMG", "BTMG", "DBU", "MTBD", "BTTP", "P2Et"], "ds": null}, {"type": "CategoricalVariable", "is_objective": false, "name": "inputs[\"Solvent\"].components[0].identifiers[0].value", "description": "Solvent", "units": null, "levels": ["2-MeTHF", "DMSO"], "ds": null}, {"type": "ContinuousVariable", "is_objective": false, "name": "outcomes[0].reaction_time.value", "description": "Residence time in seconds (s)", "units": null, "bounds": [60.0, 6000.0]}, {"type": "ContinuousVariable", "is_objective": false, "name": "conditions.temperature.setpoint.value", "description": "Reactor temperature in degrees Celsius (\u00baC)", "units": null, "bounds": [30.0, 110.0]}, {"type": "ContinuousVariable", "is_objective": true, "name": "outcomes[0].products[0].measurements[0].percentage.value", "description": "Residence time in seconds (s)", "units": null, "bounds": [0.0, 105.0]}], "transform_params": {}}, "strategy_params": {"all_experiments": {"index": [0, 1, 0, 0, 0, 0, 0, 0, 0, 0, 0, 0, 0, 0, 0, 0, 0, 0, 0, 0], "columns": [["inputs[\"Catalyst\"].components[0].identifiers[0].value", "DATA"], ["inputs[\"Base\"].components[0].identifiers[0].value", "DATA"], ["inputs[\"Solvent\"].components[0].identifiers[0].value", "DATA"], ["outcomes[0].reaction_time.value", "DATA"], ["conditions.temperature.setpoint.value", "DATA"], ["outcomes[0].products[0].measurements[0].percentage.value", "DATA"], ["computation_t", "METADATA"], ["experiment_t", "METADATA"], ["strategy", "METADATA"], ["task", "METADATA"]], "data": [["cycloPd AlPhos 4-Chlorotoluene", "TEA", "DMSO", 1545.0, 90.0, 28.35944175720215, 0.0, 0.02815389633178711, "LHS", 1.0], ["cycloPd AlPhos 4-Chlorotoluene", "TMG", "2-MeTHF", 4515.0, 50.0, 47.38068389892578, 0.0, 0.026536941528320312, "LHS", 1.0], ["cycloPd tBuBrettPhos 4-Chlorotoluene", "DBU", "DMSO", 4320.85009765625, 75.37541198730469, 70.89093780517578, 0.5866601467132568, 0.022139787673950195, "MTBO", 1.0], ["cycloPd tBuBrettPhos 4-Chlorotoluene", "BTMG", "2-MeTHF", 3688.8505859375, 44.225486755371094, 79.63116455078125, 0.6376829147338867, 0.021254777908325195, "MTBO", 1.0], ["cycloPd AlPhos 4-Chlorotoluene", "P2Et", "2-MeTHF", 5982.5380859375, 82.78766632080078, 61.44126510620117, 0.7170569896697998, 0.020233154296875, "MTBO", 1.0], ["cycloPd tBuXPhos 4-Chlorotoluene", "BTTP", "2-MeTHF", 3657.15185546875, 90.87084197998047, 70.35639190673828, 0.5344488620758057, 0.020312070846557617, "MTBO", 1.0], ["cycloPd AlPhos 4-Chlorotoluene", "BTMG", "DMSO", 1157.657958984375, 92.13490295410156, 99.60930633544922, 0.514735221862793, 0.02071404457092285, "MTBO", 1.0], ["cycloPd AlPhos 4-Chlorotoluene", "Triethylamine", "2-MeTHF", 1514.5777587890625, 103.16060638427734, 74.19143676757812, 0.6229372024536133, 0.022125244140625, "MTBO", 1.0], ["cycloPd AlPhos 4-Chlorotoluene", "Triethylamine", "DMSO", 1598.550537109375, 60.89253616333008, 53.96757888793945, 0.5864150524139404, 0.024358272552490234, "MTBO", 1.0], ["cycloPd tBuBrettPhos 4-Chlorotoluene", "DBU", "DMSO", 2283.22021484375, 76.5758285522461, 75.47303009033203, 0.6191012859344482, 0.02442002296447754, "MTBO", 1.0], ["cycloPd AlPhos 4-Chlorotoluene", "TEA", "DMSO", 2874.954833984375, 69.91719055175781, 23.16265869140625, 0.6738779544830322, 0.023424863815307617, "MTBO", 1.0], ["cycloPd tBuBrettPhos 4-Chlorotoluene", "BTMG", "DMSO", 917.628173828125, 66.25444030761719, 89.43767547607422, 0.8641097545623779, 0.021396875381469727, "MTBO", 1.0], ["cycloPd tBuXPhos 4-Chlorotoluene", "DBU", "DMSO", 3293.42431640625, 48.88257598876953, 60.76161575317383, 0.6480629444122314, 0.02036309242248535, "MTBO", 1.0], ["cycloPd tBuXPhos 4-Chlorotoluene", "TEA", "2-MeTHF", 3828.26806640625, 79.93433380126953, 27.834304809570312, 0.686729907989502, 0.021313905715942383, "MTBO", 1.0], ["cycloPd EPhos 4-Chlorotoluene", "TEA", "2-MeTHF", 5519.00390625, 79.54090881347656, 6.5962371826171875, 0.6929638385772705, 0.021430015563964844, "MTBO", 1.0], ["cycloPd tBuXPhos 4-Chlorotoluene", "TMG", "2-MeTHF", 4630.814453125, 91.97593688964844, 70.09156799316406, 0.8317372798919678, 0.024555206298828125, "MTBO", 1.0], ["cycloPd AlPhos 4-Chlorotoluene", "P2Et", "2-MeTHF", 2015.4656982421875, 34.08591842651367, 44.63897705078125, 0.6541979312896729, 0.02429962158203125, "MTBO", 1.0], ["cycloPd AlPhos 4-Chlorotoluene", "MTBD", "DMSO", 4403.8623046875, 37.88215255737305, 43.04612350463867, 0.7156171798706055, 0.02170419692993164, "MTBO", 1.0], ["cycloPd tBuXPhos 4-Chlorotoluene", "TEA", "DMSO", 1377.658447265625, 71.25048828125, 20.70421028137207, 0.6252830028533936, 0.023159027099609375, "MTBO", 1.0], ["cycloPd AlPhos 4-Chlorotoluene", "BTMG", "DMSO", 1401.0782470703125, 80.05256652832031, 96.19634246826172, 0.6098828315734863, 0.023254871368408203, "MTBO", 1.0]]}, "categorical_method": "one-hot", "task": 1}}, "experiment": {"domain": [{"type": "CategoricalVariable", "is_objective": false, "name": "inputs[\"Catalyst\"].components[0].identifiers[0].value", "description": "Catalyst", "units": null, "levels": ["cycloPd tBuXPhos 4-Chlorotoluene", "cycloPd EPhos 4-Chlorotoluene", "cycloPd AlPhos 4-Chlorotoluene", "cycloPd tBuBrettPhos 4-Chlorotoluene"], "ds": null}, {"type": "CategoricalVariable", "is_objective": false, "name": "inputs[\"Base\"].components[0].identifiers[0].value", "description": "Base", "units": null, "levels": ["TEA", "Triethylamine", "TMG", "BTMG", "DBU", "MTBD", "BTTP", "P2Et"], "ds": null}, {"type": "CategoricalVariable", "is_objective": false, "name": "inputs[\"Solvent\"].components[0].identifiers[0].value", "description": "Solvent", "units": null, "levels": ["2-MeTHF", "DMSO"], "ds": null}, {"type": "ContinuousVariable", "is_objective": false, "name": "outcomes[0].reaction_time.value", "description": "Residence time in seconds (s)", "units": null, "bounds": [60.0, 6000.0]}, {"type": "ContinuousVariable", "is_objective": false, "name": "conditions.temperature.setpoint.value", "description": "Reactor temperature in degrees Celsius (\u00baC)", "units": null, "bounds": [30.0, 110.0]}, {"type": "ContinuousVariable", "is_objective": true, "name": "outcomes[0].products[0].measurements[0].percentage.value", "description": "Residence time in seconds (s)", "units": null, "bounds": [0.0, 105.0]}], "name": "ExperimentalEmulator", "data": {"index": [0, 1, 2, 3, 4, 5, 6, 7, 8, 9, 10, 11, 12, 13, 14, 15, 16, 17, 18, 19, 20], "columns": [["inputs[\"Catalyst\"].components[0].identifiers[0].value", "DATA"], ["inputs[\"Base\"].components[0].identifiers[0].value", "DATA"], ["inputs[\"Solvent\"].components[0].identifiers[0].value", "DATA"], ["outcomes[0].reaction_time.value", "DATA"], ["conditions.temperature.setpoint.value", "DATA"], ["outcomes[0].products[0].measurements[0].percentage.value", "DATA"], ["computation_t", "METADATA"], ["experiment_t", "METADATA"], ["strategy", "METADATA"], ["task", "METADATA"]], "data": [["cycloPd AlPhos 4-Chlorotoluene", "TEA", "DMSO", 1545.0, 90.0, 28.35944175720215, 0.0, 0.02815389633178711, "LHS", 1.0], ["cycloPd AlPhos 4-Chlorotoluene", "TMG", "2-MeTHF", 4515.0, 50.0, 47.38068389892578, 0.0, 0.026536941528320312, "LHS", 1.0], ["cycloPd tBuBrettPhos 4-Chlorotoluene", "DBU", "DMSO", 4320.85009765625, 75.37541198730469, 70.89093780517578, 0.5866601467132568, 0.022139787673950195, "MTBO", 1.0], ["cycloPd tBuBrettPhos 4-Chlorotoluene", "BTMG", "2-MeTHF", 3688.8505859375, 44.225486755371094, 79.63116455078125, 0.6376829147338867, 0.021254777908325195, "MTBO", 1.0], ["cycloPd AlPhos 4-Chlorotoluene", "P2Et", "2-MeTHF", 5982.5380859375, 82.78766632080078, 61.44126510620117, 0.7170569896697998, 0.020233154296875, "MTBO", 1.0], ["cycloPd tBuXPhos 4-Chlorotoluene", "BTTP", "2-MeTHF", 3657.15185546875, 90.87084197998047, 70.35639190673828, 0.5344488620758057, 0.020312070846557617, "MTBO", 1.0], ["cycloPd AlPhos 4-Chlorotoluene", "BTMG", "DMSO", 1157.657958984375, 92.13490295410156, 99.60930633544922, 0.514735221862793, 0.02071404457092285, "MTBO", 1.0], ["cycloPd AlPhos 4-Chlorotoluene", "Triethylamine", "2-MeTHF", 1514.5777587890625, 103.16060638427734, 74.19143676757812, 0.6229372024536133, 0.022125244140625, "MTBO", 1.0], ["cycloPd AlPhos 4-Chlorotoluene", "Triethylamine", "DMSO", 1598.550537109375, 60.89253616333008, 53.96757888793945, 0.5864150524139404, 0.024358272552490234, "MTBO", 1.0], ["cycloPd tBuBrettPhos 4-Chlorotoluene", "DBU", "DMSO", 2283.22021484375, 76.5758285522461, 75.47303009033203, 0.6191012859344482, 0.02442002296447754, "MTBO", 1.0], ["cycloPd AlPhos 4-Chlorotoluene", "TEA", "DMSO", 2874.954833984375, 69.91719055175781, 23.16265869140625, 0.6738779544830322, 0.023424863815307617, "MTBO", 1.0], ["cycloPd tBuBrettPhos 4-Chlorotoluene", "BTMG", "DMSO", 917.628173828125, 66.25444030761719, 89.43767547607422, 0.8641097545623779, 0.021396875381469727, "MTBO", 1.0], ["cycloPd tBuXPhos 4-Chlorotoluene", "DBU", "DMSO", 3293.42431640625, 48.88257598876953, 60.76161575317383, 0.6480629444122314, 0.02036309242248535, "MTBO", 1.0], ["cycloPd tBuXPhos 4-Chlorotoluene", "TEA", "2-MeTHF", 3828.26806640625, 79.93433380126953, 27.834304809570312, 0.686729907989502, 0.021313905715942383, "MTBO", 1.0], ["cycloPd EPhos 4-Chlorotoluene", "TEA", "2-MeTHF", 5519.00390625, 79.54090881347656, 6.5962371826171875, 0.6929638385772705, 0.021430015563964844, "MTBO", 1.0], ["cycloPd tBuXPhos 4-Chlorotoluene", "TMG", "2-MeTHF", 4630.814453125, 91.97593688964844, 70.09156799316406, 0.8317372798919678, 0.024555206298828125, "MTBO", 1.0], ["cycloPd AlPhos 4-Chlorotoluene", "P2Et", "2-MeTHF", 2015.4656982421875, 34.08591842651367, 44.63897705078125, 0.6541979312896729, 0.02429962158203125, "MTBO", 1.0], ["cycloPd AlPhos 4-Chlorotoluene", "MTBD", "DMSO", 4403.8623046875, 37.88215255737305, 43.04612350463867, 0.7156171798706055, 0.02170419692993164, "MTBO", 1.0], ["cycloPd tBuXPhos 4-Chlorotoluene", "TEA", "DMSO", 1377.658447265625, 71.25048828125, 20.70421028137207, 0.6252830028533936, 0.023159027099609375, "MTBO", 1.0], ["cycloPd AlPhos 4-Chlorotoluene", "BTMG", "DMSO", 1401.0782470703125, 80.05256652832031, 96.19634246826172, 0.6098828315734863, 0.023254871368408203, "MTBO", 1.0], ["cycloPd AlPhos 4-Chlorotoluene", "MTBD", "2-MeTHF", 1637.20751953125, 80.88675689697266, 63.94982147216797, 1.434215784072876, 0.019758939743041992, "MTBO", 1.0]]}, "experiment_params": {"model_name": "aniline_bm", "regressor_name": "ANNRegressor", "n_features": 16, "n_examples": 131, "descriptors_features": [], "output_variable_names": ["outcomes[0].products[0].measurements[0].percentage.value"], "predictors": [{"input_preprocessor": {"num": {"mean_": [701.4394870060746, 77.56559134042391], "var_": [235931.04761351628, 793.3347318783062], "scale_": [485.7273387544871, 28.16619839236929], "n_samples_seen_": 93}}, "output_preprocessor": {"mean_": [55.14020425601993], "var_": [1725.4436660205083], "scale_": [41.538460082440565], "n_samples_seen_": 93}}, {"input_preprocessor": {"num": {"mean_": [717.7043648176295, 71.47956983504757], "var_": [250060.7267360831, 946.11496010752], "scale_": [500.06072304879444, 30.758981779433466], "n_samples_seen_": 93}}, "output_preprocessor": {"mean_": [50.112114068961915], "var_": [1815.3591003225695], "scale_": [42.60703111368556], "n_samples_seen_": 93}}, {"input_preprocessor": {"num": {"mean_": [705.5370584041515, 73.97872336367344], "var_": [243107.23788756528, 902.1816758425133], "scale_": [493.05906125693025, 30.036339255017634], "n_samples_seen_": 94}}, "output_preprocessor": {"mean_": [53.70323351287144], "var_": [1805.1382163839137], "scale_": [42.486918179410395], "n_samples_seen_": 94}}, {"input_preprocessor": {"num": {"mean_": [741.2767935407923, 75.92340420662089], "var_": [246186.9505281547, 884.2364749611769], "scale_": [496.1722992350084, 29.73611398554251], "n_samples_seen_": 94}}, "output_preprocessor": {"mean_": [52.90499311693488], "var_": [1749.589385895019], "scale_": [41.82809326152722], "n_samples_seen_": 94}}, {"input_preprocessor": {"num": {"mean_": [707.9297706928659, 72.25957444373597], "var_": [247890.93543675233, 966.5226217298738], "scale_": [497.88646842101696, 31.08894693825884], "n_samples_seen_": 94}}, "output_preprocessor": {"mean_": [54.15714759815564], "var_": [1777.1796416900258], "scale_": [42.156608517408344], "n_samples_seen_": 94}}], "clip": true}, "extras": [{}, {}, {}, {}, {}, {}, {}, {}, {}, {}, {}, {}, {}, {}, {}, {}, {}, {}, {}, {}, {}, {}, {}, {}, {}, {}, {}, {}, {}, {}, {}, {}, {}, {}, {}, {}, {}, {}, {}, {}, {}, {}]}}