{"runner": {"num_initial_experiments": null, "max_iterations": 20, "batch_size": 1, "f_tol": 1e-05, "max_restarts": 0}, "strategy": {"name": "MTBO", "transform": {"transform_domain": [{"type": "CategoricalVariable", "is_objective": false, "name": "inputs[\"Catalyst\"].components[0].identifiers[0].value", "description": "Catalyst", "units": null, "levels": ["cycloPd tBuXPhos 4-Chlorotoluene", "cycloPd EPhos 4-Chlorotoluene", "cycloPd AlPhos 4-Chlorotoluene", "cycloPd tBuBrettPhos 4-Chlorotoluene"], "ds": null}, {"type": "CategoricalVariable", "is_objective": false, "name": "inputs[\"Base\"].components[0].identifiers[0].value", "description": "Base", "units": null, "levels": ["TEA", "Triethylamine", "TMG", "BTMG", "DBU", "MTBD", "BTTP", "P2Et"], "ds": null}, {"type": "CategoricalVariable", "is_objective": false, "name": "inputs[\"Solvent\"].components[0].identifiers[0].value", "description": "Solvent", "units": null, "levels": ["2-MeTHF", "DMSO"], "ds": null}, {"type": "ContinuousVariable", "is_objective": false, "name": "outcomes[0].reaction_time.value", "description": "Residence time in seconds (s)", "units": null, "bounds": [60.0, 6000.0]}, {"type": "ContinuousVariable", "is_objective": false, "name": "conditions.temperature.setpoint.value", "description": "Reactor temperature in degrees Celsius (\u00baC)", "units": null, "bounds": [30.0, 110.0]}, {"type": "ContinuousVariable", "is_objective": true, "name": "outcomes[0].products[0].measurements[0].percentage.value", "description": "Residence time in seconds (s)", "units": null, "bounds": [0.0, 105.0]}], "name": "Transform", "domain": [{"type": "CategoricalVariable", "is_objective": false, "name": "inputs[\"Catalyst\"].components[0].identifiers[0].value", "description": "Catalyst", "units": null, "levels": ["cycloPd tBuXPhos 4-Chlorotoluene", "cycloPd EPhos 4-Chlorotoluene", "cycloPd AlPhos 4-Chlorotoluene", "cycloPd tBuBrettPhos 4-Chlorotoluene"], "ds": null}, {"type": "CategoricalVariable", "is_objective": false, "name": "inputs[\"Base\"].components[0].identifiers[0].value", "description": "Base", "units": null, "levels": ["TEA", "Triethylamine", "TMG", "BTMG", "DBU", "MTBD", "BTTP", "P2Et"], "ds": null}, {"type": "CategoricalVariable", "is_objective": false, "name": "inputs[\"Solvent\"].components[0].identifiers[0].value", "description": "Solvent", "units": null, "levels": ["2-MeTHF", "DMSO"], "ds": null}, {"type": "ContinuousVariable", "is_objective": false, "name": "outcomes[0].reaction_time.value", "description": "Residence time in seconds (s)", "units": null, "bounds": [60.0, 6000.0]}, {"type": "ContinuousVariable", "is_objective": false, "name": "conditions.temperature.setpoint.value", "description": "Reactor temperature in degrees Celsius (\u00baC)", "units": null, "bounds": [30.0, 110.0]}, {"type": "ContinuousVariable", "is_objective": true, "name": "outcomes[0].products[0].measurements[0].percentage.value", "description": "Residence time in seconds (s)", "units": null, "bounds": [0.0, 105.0]}], "transform_params": {}}, "strategy_params": {"all_experiments": {"index": [0, 1, 0, 0, 0, 0, 0, 0, 0, 0, 0, 0, 0, 0, 0, 0, 0, 0, 0, 0], "columns": [["inputs[\"Catalyst\"].components[0].identifiers[0].value", "DATA"], ["inputs[\"Base\"].components[0].identifiers[0].value", "DATA"], ["inputs[\"Solvent\"].components[0].identifiers[0].value", "DATA"], ["outcomes[0].reaction_time.value", "DATA"], ["conditions.temperature.setpoint.value", "DATA"], ["outcomes[0].products[0].measurements[0].percentage.value", "DATA"], ["computation_t", "METADATA"], ["experiment_t", "METADATA"], ["strategy", "METADATA"], ["task", "METADATA"]], "data": [["cycloPd AlPhos 4-Chlorotoluene", "Triethylamine", "2-MeTHF", 1545.0, 90.0, 74.38108825683594, 0.0, 0.02418828010559082, "LHS", 1.0], ["cycloPd EPhos 4-Chlorotoluene", "MTBD", "DMSO", 4515.0, 50.0, 40.069278717041016, 0.0, 0.023044824600219727, "LHS", 1.0], ["cycloPd AlPhos 4-Chlorotoluene", "Triethylamine", "2-MeTHF", 1672.6298828125, 86.26062774658203, 73.053466796875, 0.8009788990020752, 0.02038407325744629, "MTBO", 1.0], ["cycloPd AlPhos 4-Chlorotoluene", "BTMG", "2-MeTHF", 1887.0361328125, 90.12635040283203, 102.10992431640625, 1.552164077758789, 0.019531965255737305, "MTBO", 1.0], ["cycloPd AlPhos 4-Chlorotoluene", "MTBD", "2-MeTHF", 2002.039306640625, 72.90888977050781, 65.27825927734375, 1.0165209770202637, 0.019652843475341797, "MTBO", 1.0], ["cycloPd AlPhos 4-Chlorotoluene", "TMG", "2-MeTHF", 1805.951171875, 87.0701904296875, 63.15269088745117, 0.4343149662017822, 0.0198972225189209, "MTBO", 1.0], ["cycloPd AlPhos 4-Chlorotoluene", "TMG", "2-MeTHF", 1987.4434814453125, 76.61494445800781, 55.8709602355957, 1.3065900802612305, 0.021017789840698242, "MTBO", 1.0], ["cycloPd AlPhos 4-Chlorotoluene", "TMG", "2-MeTHF", 2297.55810546875, 88.43441772460938, 63.276329040527344, 0.7432281970977783, 0.019176959991455078, "MTBO", 1.0], ["cycloPd AlPhos 4-Chlorotoluene", "MTBD", "2-MeTHF", 2028.08251953125, 84.595458984375, 71.08599090576172, 1.0161468982696533, 0.01995706558227539, "MTBO", 1.0], ["cycloPd AlPhos 4-Chlorotoluene", "BTMG", "2-MeTHF", 1835.58154296875, 85.09233093261719, 100.88272857666016, 1.5645949840545654, 0.019748210906982422, "MTBO", 1.0], ["cycloPd AlPhos 4-Chlorotoluene", "BTMG", "2-MeTHF", 1680.185546875, 89.61805725097656, 102.61827087402344, 0.7579388618469238, 0.019417285919189453, "MTBO", 1.0], ["cycloPd AlPhos 4-Chlorotoluene", "BTMG", "2-MeTHF", 2213.656494140625, 85.0943603515625, 99.54078674316406, 0.8670980930328369, 0.020639896392822266, "MTBO", 1.0], ["cycloPd AlPhos 4-Chlorotoluene", "MTBD", "2-MeTHF", 2851.77099609375, 79.70111846923828, 70.02098846435547, 0.8253250122070312, 0.019399166107177734, "MTBO", 1.0], ["cycloPd tBuBrettPhos 4-Chlorotoluene", "BTTP", "2-MeTHF", 985.08935546875, 79.17757415771484, 65.8788833618164, 1.1760969161987305, 0.018945932388305664, "MTBO", 1.0], ["cycloPd AlPhos 4-Chlorotoluene", "BTMG", "2-MeTHF", 1847.8575439453125, 88.03167724609375, 101.66486358642578, 1.1377060413360596, 0.019652128219604492, "MTBO", 1.0], ["cycloPd tBuBrettPhos 4-Chlorotoluene", "DBU", "2-MeTHF", 397.3350830078125, 99.12889099121094, 94.53131103515625, 0.5638551712036133, 0.018941164016723633, "MTBO", 1.0], ["cycloPd AlPhos 4-Chlorotoluene", "BTMG", "2-MeTHF", 2496.8232421875, 95.13280487060547, 101.46465301513672, 0.7894461154937744, 0.018534183502197266, "MTBO", 1.0], ["cycloPd AlPhos 4-Chlorotoluene", "BTMG", "2-MeTHF", 1858.77587890625, 100.79191589355469, 104.60444641113281, 0.7606320381164551, 0.019163131713867188, "MTBO", 1.0], ["cycloPd tBuBrettPhos 4-Chlorotoluene", "DBU", "2-MeTHF", 1134.7939453125, 110.0, 104.02288818359375, 0.8463542461395264, 0.01949787139892578, "MTBO", 1.0], ["cycloPd tBuBrettPhos 4-Chlorotoluene", "DBU", "2-MeTHF", 1372.383056640625, 101.11080932617188, 97.78273010253906, 1.1929209232330322, 0.020669937133789062, "MTBO", 1.0]]}, "categorical_method": "one-hot", "task": 1}}, "experiment": {"domain": [{"type": "CategoricalVariable", "is_objective": false, "name": "inputs[\"Catalyst\"].components[0].identifiers[0].value", "description": "Catalyst", "units": null, "levels": ["cycloPd tBuXPhos 4-Chlorotoluene", "cycloPd EPhos 4-Chlorotoluene", "cycloPd AlPhos 4-Chlorotoluene", "cycloPd tBuBrettPhos 4-Chlorotoluene"], "ds": null}, {"type": "CategoricalVariable", "is_objective": false, "name": "inputs[\"Base\"].components[0].identifiers[0].value", "description": "Base", "units": null, "levels": ["TEA", "Triethylamine", "TMG", "BTMG", "DBU", "MTBD", "BTTP", "P2Et"], "ds": null}, {"type": "CategoricalVariable", "is_objective": false, "name": "inputs[\"Solvent\"].components[0].identifiers[0].value", "description": "Solvent", "units": null, "levels": ["2-MeTHF", "DMSO"], "ds": null}, {"type": "ContinuousVariable", "is_objective": false, "name": "outcomes[0].reaction_time.value", "description": "Residence time in seconds (s)", "units": null, "bounds": [60.0, 6000.0]}, {"type": "ContinuousVariable", "is_objective": false, "name": "conditions.temperature.setpoint.value", "description": "Reactor temperature in degrees Celsius (\u00baC)", "units": null, "bounds": [30.0, 110.0]}, {"type": "ContinuousVariable", "is_objective": true, "name": "outcomes[0].products[0].measurements[0].percentage.value", "description": "Residence time in seconds (s)", "units": null, "bounds": [0.0, 105.0]}], "name": "ExperimentalEmulator", "data": {"index": [0, 1, 2, 3, 4, 5, 6, 7, 8, 9, 10, 11, 12, 13, 14, 15, 16, 17, 18, 19, 20], "columns": [["inputs[\"Catalyst\"].components[0].identifiers[0].value", "DATA"], ["inputs[\"Base\"].components[0].identifiers[0].value", "DATA"], ["inputs[\"Solvent\"].components[0].identifiers[0].value", "DATA"], ["outcomes[0].reaction_time.value", "DATA"], ["conditions.temperature.setpoint.value", "DATA"], ["outcomes[0].products[0].measurements[0].percentage.value", "DATA"], ["computation_t", "METADATA"], ["experiment_t", "METADATA"], ["strategy", "METADATA"], ["task", "METADATA"]], "data": [["cycloPd AlPhos 4-Chlorotoluene", "Triethylamine", "2-MeTHF", 1545.0, 90.0, 74.38108825683594, 0.0, 0.02418828010559082, "LHS", 1.0], ["cycloPd EPhos 4-Chlorotoluene", "MTBD", "DMSO", 4515.0, 50.0, 40.069278717041016, 0.0, 0.023044824600219727, "LHS", 1.0], ["cycloPd AlPhos 4-Chlorotoluene", "Triethylamine", "2-MeTHF", 1672.6298828125, 86.26062774658203, 73.053466796875, 0.8009788990020752, 0.02038407325744629, "MTBO", 1.0], ["cycloPd AlPhos 4-Chlorotoluene", "BTMG", "2-MeTHF", 1887.0361328125, 90.12635040283203, 102.10992431640625, 1.552164077758789, 0.019531965255737305, "MTBO", 1.0], ["cycloPd AlPhos 4-Chlorotoluene", "MTBD", "2-MeTHF", 2002.039306640625, 72.90888977050781, 65.27825927734375, 1.0165209770202637, 0.019652843475341797, "MTBO", 1.0], ["cycloPd AlPhos 4-Chlorotoluene", "TMG", "2-MeTHF", 1805.951171875, 87.0701904296875, 63.15269088745117, 0.4343149662017822, 0.0198972225189209, "MTBO", 1.0], ["cycloPd AlPhos 4-Chlorotoluene", "TMG", "2-MeTHF", 1987.4434814453125, 76.61494445800781, 55.8709602355957, 1.3065900802612305, 0.021017789840698242, "MTBO", 1.0], ["cycloPd AlPhos 4-Chlorotoluene", "TMG", "2-MeTHF", 2297.55810546875, 88.43441772460938, 63.276329040527344, 0.7432281970977783, 0.019176959991455078, "MTBO", 1.0], ["cycloPd AlPhos 4-Chlorotoluene", "MTBD", "2-MeTHF", 2028.08251953125, 84.595458984375, 71.08599090576172, 1.0161468982696533, 0.01995706558227539, "MTBO", 1.0], ["cycloPd AlPhos 4-Chlorotoluene", "BTMG", "2-MeTHF", 1835.58154296875, 85.09233093261719, 100.88272857666016, 1.5645949840545654, 0.019748210906982422, "MTBO", 1.0], ["cycloPd AlPhos 4-Chlorotoluene", "BTMG", "2-MeTHF", 1680.185546875, 89.61805725097656, 102.61827087402344, 0.7579388618469238, 0.019417285919189453, "MTBO", 1.0], ["cycloPd AlPhos 4-Chlorotoluene", "BTMG", "2-MeTHF", 2213.656494140625, 85.0943603515625, 99.54078674316406, 0.8670980930328369, 0.020639896392822266, "MTBO", 1.0], ["cycloPd AlPhos 4-Chlorotoluene", "MTBD", "2-MeTHF", 2851.77099609375, 79.70111846923828, 70.02098846435547, 0.8253250122070312, 0.019399166107177734, "MTBO", 1.0], ["cycloPd tBuBrettPhos 4-Chlorotoluene", "BTTP", "2-MeTHF", 985.08935546875, 79.17757415771484, 65.8788833618164, 1.1760969161987305, 0.018945932388305664, "MTBO", 1.0], ["cycloPd AlPhos 4-Chlorotoluene", "BTMG", "2-MeTHF", 1847.8575439453125, 88.03167724609375, 101.66486358642578, 1.1377060413360596, 0.019652128219604492, "MTBO", 1.0], ["cycloPd tBuBrettPhos 4-Chlorotoluene", "DBU", "2-MeTHF", 397.3350830078125, 99.12889099121094, 94.53131103515625, 0.5638551712036133, 0.018941164016723633, "MTBO", 1.0], ["cycloPd AlPhos 4-Chlorotoluene", "BTMG", "2-MeTHF", 2496.8232421875, 95.13280487060547, 101.46465301513672, 0.7894461154937744, 0.018534183502197266, "MTBO", 1.0], ["cycloPd AlPhos 4-Chlorotoluene", "BTMG", "2-MeTHF", 1858.77587890625, 100.79191589355469, 104.60444641113281, 0.7606320381164551, 0.019163131713867188, "MTBO", 1.0], ["cycloPd tBuBrettPhos 4-Chlorotoluene", "DBU", "2-MeTHF", 1134.7939453125, 110.0, 104.02288818359375, 0.8463542461395264, 0.01949787139892578, "MTBO", 1.0], ["cycloPd tBuBrettPhos 4-Chlorotoluene", "DBU", "2-MeTHF", 1372.383056640625, 101.11080932617188, 97.78273010253906, 1.1929209232330322, 0.020669937133789062, "MTBO", 1.0], ["cycloPd AlPhos 4-Chlorotoluene", "BTMG", "2-MeTHF", 1305.4822998046875, 102.9814453125, 105.0, 0.9967653751373291, 0.018365859985351562, "MTBO", 1.0]]}, "experiment_params": {"model_name": "aniline_bm", "regressor_name": "ANNRegressor", "n_features": 16, "n_examples": 131, "descriptors_features": [], "output_variable_names": ["outcomes[0].products[0].measurements[0].percentage.value"], "predictors": [{"input_preprocessor": {"num": {"mean_": [718.8831836331275, 75.37311820573704], "var_": [245854.31572057193, 919.6630404802107], "scale_": [495.8369850269057, 30.325946654312553], "n_samples_seen_": 93}}, "output_preprocessor": {"mean_": [58.08766073949875], "var_": [1714.8116458295494], "scale_": [41.41028430027436], "n_samples_seen_": 93}}, {"input_preprocessor": {"num": {"mean_": [669.3959776355374, 74.89354832967122], "var_": [226173.06217903335, 908.93759199372], "scale_": [475.5765576424403, 30.148591874144305], "n_samples_seen_": 93}}, "output_preprocessor": {"mean_": [50.95959441419891], "var_": [1862.0080393514324], "scale_": [43.15099117461188], "n_samples_seen_": 93}}, {"input_preprocessor": {"num": {"mean_": [707.537096956943, 75.98936166154577], "var_": [251947.2798595299, 887.7109493845179], "scale_": [501.9435026569523, 29.79447850499347], "n_samples_seen_": 94}}, "output_preprocessor": {"mean_": [52.9166117479351], "var_": [1752.4699447560818], "scale_": [41.8625124037734], "n_samples_seen_": 94}}, {"input_preprocessor": {"num": {"mean_": [655.0339700414779, 75.92340420662089], "var_": [244439.92407050938, 864.6886026207515], "scale_": [494.40866099868174, 29.405587948904397], "n_samples_seen_": 94}}, "output_preprocessor": {"mean_": [50.310789258001336], "var_": [1792.2312681915912], "scale_": [42.33475248766185], "n_samples_seen_": 94}}, {"input_preprocessor": {"num": {"mean_": [704.9342480111629, 72.5340424801441], "var_": [243683.67799888543, 913.3218190829967], "scale_": [493.64326998236834, 30.22121471885266], "n_samples_seen_": 94}}, "output_preprocessor": {"mean_": [50.13164271897775], "var_": [1781.8666189249525], "scale_": [42.21216197880597], "n_samples_seen_": 94}}], "clip": true}, "extras": [{}, {}, {}, {}, {}, {}, {}, {}, {}, {}, {}, {}, {}, {}, {}, {}, {}, {}, {}, {}, {}, {}, {}, {}, {}, {}, {}, {}, {}, {}, {}, {}, {}, {}, {}, {}, {}, {}, {}, {}, {}, {}]}}