{"runner": {"num_initial_experiments": null, "max_iterations": 20, "batch_size": 1, "f_tol": 1e-05, "max_restarts": 0}, "strategy": {"name": "MTBO", "transform": {"transform_domain": [{"type": "CategoricalVariable", "is_objective": false, "name": "inputs[\"Catalyst\"].components[0].identifiers[0].value", "description": "Catalyst", "units": null, "levels": ["cycloPd tBuXPhos 4-Chlorotoluene", "cycloPd EPhos 4-Chlorotoluene", "cycloPd AlPhos 4-Chlorotoluene", "cycloPd tBuBrettPhos 4-Chlorotoluene"], "ds": null}, {"type": "CategoricalVariable", "is_objective": false, "name": "inputs[\"Base\"].components[0].identifiers[0].value", "description": "Base", "units": null, "levels": ["TEA", "Triethylamine", "TMG", "BTMG", "DBU", "MTBD", "BTTP", "P2Et"], "ds": null}, {"type": "CategoricalVariable", "is_objective": false, "name": "inputs[\"Solvent\"].components[0].identifiers[0].value", "description": "Solvent", "units": null, "levels": ["2-MeTHF", "DMSO"], "ds": null}, {"type": "ContinuousVariable", "is_objective": false, "name": "outcomes[0].reaction_time.value", "description": "Residence time in seconds (s)", "units": null, "bounds": [60.0, 6000.0]}, {"type": "ContinuousVariable", "is_objective": false, "name": "conditions.temperature.setpoint.value", "description": "Reactor temperature in degrees Celsius (\u00baC)", "units": null, "bounds": [30.0, 110.0]}, {"type": "ContinuousVariable", "is_objective": true, "name": "outcomes[0].products[0].measurements[0].percentage.value", "description": "Residence time in seconds (s)", "units": null, "bounds": [0.0, 105.0]}], "name": "Transform", "domain": [{"type": "CategoricalVariable", "is_objective": false, "name": "inputs[\"Catalyst\"].components[0].identifiers[0].value", "description": "Catalyst", "units": null, "levels": ["cycloPd tBuXPhos 4-Chlorotoluene", "cycloPd EPhos 4-Chlorotoluene", "cycloPd AlPhos 4-Chlorotoluene", "cycloPd tBuBrettPhos 4-Chlorotoluene"], "ds": null}, {"type": "CategoricalVariable", "is_objective": false, "name": "inputs[\"Base\"].components[0].identifiers[0].value", "description": "Base", "units": null, "levels": ["TEA", "Triethylamine", "TMG", "BTMG", "DBU", "MTBD", "BTTP", "P2Et"], "ds": null}, {"type": "CategoricalVariable", "is_objective": false, "name": "inputs[\"Solvent\"].components[0].identifiers[0].value", "description": "Solvent", "units": null, "levels": ["2-MeTHF", "DMSO"], "ds": null}, {"type": "ContinuousVariable", "is_objective": false, "name": "outcomes[0].reaction_time.value", "description": "Residence time in seconds (s)", "units": null, "bounds": [60.0, 6000.0]}, {"type": "ContinuousVariable", "is_objective": false, "name": "conditions.temperature.setpoint.value", "description": "Reactor temperature in degrees Celsius (\u00baC)", "units": null, "bounds": [30.0, 110.0]}, {"type": "ContinuousVariable", "is_objective": true, "name": "outcomes[0].products[0].measurements[0].percentage.value", "description": "Residence time in seconds (s)", "units": null, "bounds": [0.0, 105.0]}], "transform_params": {}}, "strategy_params": {"all_experiments": {"index": [0, 1, 0, 0, 0, 0, 0, 0, 0, 0, 0, 0, 0, 0, 0, 0, 0, 0, 0, 0], "columns": [["inputs[\"Catalyst\"].components[0].identifiers[0].value", "DATA"], ["inputs[\"Base\"].components[0].identifiers[0].value", "DATA"], ["inputs[\"Solvent\"].components[0].identifiers[0].value", "DATA"], ["outcomes[0].reaction_time.value", "DATA"], ["conditions.temperature.setpoint.value", "DATA"], ["outcomes[0].products[0].measurements[0].percentage.value", "DATA"], ["computation_t", "METADATA"], ["experiment_t", "METADATA"], ["strategy", "METADATA"], ["task", "METADATA"]], "data": [["cycloPd tBuBrettPhos 4-Chlorotoluene", "BTTP", "2-MeTHF", 4515.0, 90.0, 75.54771423339844, 0.0, 0.023090839385986328, "LHS", 1.0], ["cycloPd tBuBrettPhos 4-Chlorotoluene", "Triethylamine", "2-MeTHF", 1545.0, 50.0, 54.71754837036133, 0.0, 0.02180314064025879, "LHS", 1.0], ["cycloPd tBuBrettPhos 4-Chlorotoluene", "MTBD", "2-MeTHF", 4459.63427734375, 89.8115463256836, 78.55342864990234, 1.4579341411590576, 0.018352985382080078, "MTBO", 1.0], ["cycloPd tBuBrettPhos 4-Chlorotoluene", "MTBD", "2-MeTHF", 3676.779052734375, 88.11174011230469, 76.1997299194336, 1.1377861499786377, 0.019875288009643555, "MTBO", 1.0], ["cycloPd tBuBrettPhos 4-Chlorotoluene", "BTTP", "2-MeTHF", 3800.359375, 82.75249481201172, 71.17015075683594, 1.2410228252410889, 0.019021034240722656, "MTBO", 1.0], ["cycloPd tBuBrettPhos 4-Chlorotoluene", "BTTP", "2-MeTHF", 4699.08935546875, 78.43084716796875, 70.91255950927734, 1.458198070526123, 0.01910400390625, "MTBO", 1.0], ["cycloPd tBuBrettPhos 4-Chlorotoluene", "MTBD", "2-MeTHF", 4251.9169921875, 79.57696533203125, 73.50904846191406, 2.3078978061676025, 0.020246028900146484, "MTBO", 1.0], ["cycloPd tBuBrettPhos 4-Chlorotoluene", "MTBD", "2-MeTHF", 2944.6376953125, 74.74832916259766, 68.5346450805664, 2.3199827671051025, 0.01967000961303711, "MTBO", 1.0], ["cycloPd tBuBrettPhos 4-Chlorotoluene", "MTBD", "2-MeTHF", 1310.060302734375, 65.55803680419922, 61.300193786621094, 1.3914589881896973, 0.020420074462890625, "MTBO", 1.0], ["cycloPd tBuBrettPhos 4-Chlorotoluene", "BTMG", "2-MeTHF", 4096.93359375, 85.37985229492188, 96.96632385253906, 2.020697832107544, 0.019784927368164062, "MTBO", 1.0], ["cycloPd tBuBrettPhos 4-Chlorotoluene", "BTMG", "2-MeTHF", 3571.25146484375, 79.37307739257812, 96.3338851928711, 1.692026138305664, 0.01950216293334961, "MTBO", 1.0], ["cycloPd tBuBrettPhos 4-Chlorotoluene", "DBU", "2-MeTHF", 3442.148681640625, 79.26018524169922, 79.2982406616211, 0.9931540489196777, 0.0186460018157959, "MTBO", 1.0], ["cycloPd tBuBrettPhos 4-Chlorotoluene", "BTMG", "2-MeTHF", 3486.24609375, 87.8785629272461, 98.24687194824219, 1.4513850212097168, 0.018996000289916992, "MTBO", 1.0], ["cycloPd tBuBrettPhos 4-Chlorotoluene", "BTMG", "2-MeTHF", 3678.4326171875, 85.06782531738281, 97.4246597290039, 1.5175838470458984, 0.019708871841430664, "MTBO", 1.0], ["cycloPd tBuBrettPhos 4-Chlorotoluene", "BTMG", "2-MeTHF", 2814.3974609375, 82.22149658203125, 97.80989837646484, 1.5219991207122803, 0.019678831100463867, "MTBO", 1.0], ["cycloPd tBuBrettPhos 4-Chlorotoluene", "BTMG", "2-MeTHF", 3274.0185546875, 84.20621490478516, 97.74119567871094, 1.3509798049926758, 0.019855737686157227, "MTBO", 1.0], ["cycloPd tBuBrettPhos 4-Chlorotoluene", "TEA", "2-MeTHF", 1103.7535400390625, 59.8906364440918, 10.267632484436035, 0.7978792190551758, 0.0191650390625, "MTBO", 1.0], ["cycloPd tBuBrettPhos 4-Chlorotoluene", "BTTP", "2-MeTHF", 6000.0, 101.42152404785156, 80.4387435913086, 0.9206609725952148, 0.020617008209228516, "MTBO", 1.0], ["cycloPd tBuBrettPhos 4-Chlorotoluene", "DBU", "2-MeTHF", 4774.7841796875, 93.57103729248047, 85.80040740966797, 0.9448368549346924, 0.020513057708740234, "MTBO", 1.0], ["cycloPd tBuBrettPhos 4-Chlorotoluene", "MTBD", "2-MeTHF", 6000.0, 105.20633697509766, 85.40544128417969, 1.238861083984375, 0.02095794677734375, "MTBO", 1.0]]}, "categorical_method": "one-hot", "task": 1}}, "experiment": {"domain": [{"type": "CategoricalVariable", "is_objective": false, "name": "inputs[\"Catalyst\"].components[0].identifiers[0].value", "description": "Catalyst", "units": null, "levels": ["cycloPd tBuXPhos 4-Chlorotoluene", "cycloPd EPhos 4-Chlorotoluene", "cycloPd AlPhos 4-Chlorotoluene", "cycloPd tBuBrettPhos 4-Chlorotoluene"], "ds": null}, {"type": "CategoricalVariable", "is_objective": false, "name": "inputs[\"Base\"].components[0].identifiers[0].value", "description": "Base", "units": null, "levels": ["TEA", "Triethylamine", "TMG", "BTMG", "DBU", "MTBD", "BTTP", "P2Et"], "ds": null}, {"type": "CategoricalVariable", "is_objective": false, "name": "inputs[\"Solvent\"].components[0].identifiers[0].value", "description": "Solvent", "units": null, "levels": ["2-MeTHF", "DMSO"], "ds": null}, {"type": "ContinuousVariable", "is_objective": false, "name": "outcomes[0].reaction_time.value", "description": "Residence time in seconds (s)", "units": null, "bounds": [60.0, 6000.0]}, {"type": "ContinuousVariable", "is_objective": false, "name": "conditions.temperature.setpoint.value", "description": "Reactor temperature in degrees Celsius (\u00baC)", "units": null, "bounds": [30.0, 110.0]}, {"type": "ContinuousVariable", "is_objective": true, "name": "outcomes[0].products[0].measurements[0].percentage.value", "description": "Residence time in seconds (s)", "units": null, "bounds": [0.0, 105.0]}], "name": "ExperimentalEmulator", "data": {"index": [0, 1, 2, 3, 4, 5, 6, 7, 8, 9, 10, 11, 12, 13, 14, 15, 16, 17, 18, 19, 20], "columns": [["inputs[\"Catalyst\"].components[0].identifiers[0].value", "DATA"], ["inputs[\"Base\"].components[0].identifiers[0].value", "DATA"], ["inputs[\"Solvent\"].components[0].identifiers[0].value", "DATA"], ["outcomes[0].reaction_time.value", "DATA"], ["conditions.temperature.setpoint.value", "DATA"], ["outcomes[0].products[0].measurements[0].percentage.value", "DATA"], ["computation_t", "METADATA"], ["experiment_t", "METADATA"], ["strategy", "METADATA"], ["task", "METADATA"]], "data": [["cycloPd tBuBrettPhos 4-Chlorotoluene", "BTTP", "2-MeTHF", 4515.0, 90.0, 75.54771423339844, 0.0, 0.023090839385986328, "LHS", 1.0], ["cycloPd tBuBrettPhos 4-Chlorotoluene", "Triethylamine", "2-MeTHF", 1545.0, 50.0, 54.71754837036133, 0.0, 0.02180314064025879, "LHS", 1.0], ["cycloPd tBuBrettPhos 4-Chlorotoluene", "MTBD", "2-MeTHF", 4459.63427734375, 89.8115463256836, 78.55342864990234, 1.4579341411590576, 0.018352985382080078, "MTBO", 1.0], ["cycloPd tBuBrettPhos 4-Chlorotoluene", "MTBD", "2-MeTHF", 3676.779052734375, 88.11174011230469, 76.1997299194336, 1.1377861499786377, 0.019875288009643555, "MTBO", 1.0], ["cycloPd tBuBrettPhos 4-Chlorotoluene", "BTTP", "2-MeTHF", 3800.359375, 82.75249481201172, 71.17015075683594, 1.2410228252410889, 0.019021034240722656, "MTBO", 1.0], ["cycloPd tBuBrettPhos 4-Chlorotoluene", "BTTP", "2-MeTHF", 4699.08935546875, 78.43084716796875, 70.91255950927734, 1.458198070526123, 0.01910400390625, "MTBO", 1.0], ["cycloPd tBuBrettPhos 4-Chlorotoluene", "MTBD", "2-MeTHF", 4251.9169921875, 79.57696533203125, 73.50904846191406, 2.3078978061676025, 0.020246028900146484, "MTBO", 1.0], ["cycloPd tBuBrettPhos 4-Chlorotoluene", "MTBD", "2-MeTHF", 2944.6376953125, 74.74832916259766, 68.5346450805664, 2.3199827671051025, 0.01967000961303711, "MTBO", 1.0], ["cycloPd tBuBrettPhos 4-Chlorotoluene", "MTBD", "2-MeTHF", 1310.060302734375, 65.55803680419922, 61.300193786621094, 1.3914589881896973, 0.020420074462890625, "MTBO", 1.0], ["cycloPd tBuBrettPhos 4-Chlorotoluene", "BTMG", "2-MeTHF", 4096.93359375, 85.37985229492188, 96.96632385253906, 2.020697832107544, 0.019784927368164062, "MTBO", 1.0], ["cycloPd tBuBrettPhos 4-Chlorotoluene", "BTMG", "2-MeTHF", 3571.25146484375, 79.37307739257812, 96.3338851928711, 1.692026138305664, 0.01950216293334961, "MTBO", 1.0], ["cycloPd tBuBrettPhos 4-Chlorotoluene", "DBU", "2-MeTHF", 3442.148681640625, 79.26018524169922, 79.2982406616211, 0.9931540489196777, 0.0186460018157959, "MTBO", 1.0], ["cycloPd tBuBrettPhos 4-Chlorotoluene", "BTMG", "2-MeTHF", 3486.24609375, 87.8785629272461, 98.24687194824219, 1.4513850212097168, 0.018996000289916992, "MTBO", 1.0], ["cycloPd tBuBrettPhos 4-Chlorotoluene", "BTMG", "2-MeTHF", 3678.4326171875, 85.06782531738281, 97.4246597290039, 1.5175838470458984, 0.019708871841430664, "MTBO", 1.0], ["cycloPd tBuBrettPhos 4-Chlorotoluene", "BTMG", "2-MeTHF", 2814.3974609375, 82.22149658203125, 97.80989837646484, 1.5219991207122803, 0.019678831100463867, "MTBO", 1.0], ["cycloPd tBuBrettPhos 4-Chlorotoluene", "BTMG", "2-MeTHF", 3274.0185546875, 84.20621490478516, 97.74119567871094, 1.3509798049926758, 0.019855737686157227, "MTBO", 1.0], ["cycloPd tBuBrettPhos 4-Chlorotoluene", "TEA", "2-MeTHF", 1103.7535400390625, 59.8906364440918, 10.267632484436035, 0.7978792190551758, 0.0191650390625, "MTBO", 1.0], ["cycloPd tBuBrettPhos 4-Chlorotoluene", "BTTP", "2-MeTHF", 6000.0, 101.42152404785156, 80.4387435913086, 0.9206609725952148, 0.020617008209228516, "MTBO", 1.0], ["cycloPd tBuBrettPhos 4-Chlorotoluene", "DBU", "2-MeTHF", 4774.7841796875, 93.57103729248047, 85.80040740966797, 0.9448368549346924, 0.020513057708740234, "MTBO", 1.0], ["cycloPd tBuBrettPhos 4-Chlorotoluene", "MTBD", "2-MeTHF", 6000.0, 105.20633697509766, 85.40544128417969, 1.238861083984375, 0.02095794677734375, "MTBO", 1.0], ["cycloPd tBuBrettPhos 4-Chlorotoluene", "BTMG", "2-MeTHF", 4950.689453125, 97.97053527832031, 98.48632049560547, 1.1099052429199219, 0.01929616928100586, "MTBO", 1.0]]}, "experiment_params": {"model_name": "aniline_bm", "regressor_name": "ANNRegressor", "n_features": 16, "n_examples": 131, "descriptors_features": [], "output_variable_names": ["outcomes[0].products[0].measurements[0].percentage.value"], "predictors": [{"input_preprocessor": {"num": {"mean_": [718.8831836331275, 75.37311820573704], "var_": [245854.31572057193, 919.6630404802107], "scale_": [495.8369850269057, 30.325946654312553], "n_samples_seen_": 93}}, "output_preprocessor": {"mean_": [58.08766073949875], "var_": [1714.8116458295494], "scale_": [41.41028430027436], "n_samples_seen_": 93}}, {"input_preprocessor": {"num": {"mean_": [669.3959776355374, 74.89354832967122], "var_": [226173.06217903335, 908.93759199372], "scale_": [475.5765576424403, 30.148591874144305], "n_samples_seen_": 93}}, "output_preprocessor": {"mean_": [50.95959441419891], "var_": [1862.0080393514324], "scale_": [43.15099117461188], "n_samples_seen_": 93}}, {"input_preprocessor": {"num": {"mean_": [707.537096956943, 75.98936166154577], "var_": [251947.2798595299, 887.7109493845179], "scale_": [501.9435026569523, 29.79447850499347], "n_samples_seen_": 94}}, "output_preprocessor": {"mean_": [52.9166117479351], "var_": [1752.4699447560818], "scale_": [41.8625124037734], "n_samples_seen_": 94}}, {"input_preprocessor": {"num": {"mean_": [655.0339700414779, 75.92340420662089], "var_": [244439.92407050938, 864.6886026207515], "scale_": [494.40866099868174, 29.405587948904397], "n_samples_seen_": 94}}, "output_preprocessor": {"mean_": [50.310789258001336], "var_": [1792.2312681915912], "scale_": [42.33475248766185], "n_samples_seen_": 94}}, {"input_preprocessor": {"num": {"mean_": [704.9342480111629, 72.5340424801441], "var_": [243683.67799888543, 913.3218190829967], "scale_": [493.64326998236834, 30.22121471885266], "n_samples_seen_": 94}}, "output_preprocessor": {"mean_": [50.13164271897775], "var_": [1781.8666189249525], "scale_": [42.21216197880597], "n_samples_seen_": 94}}], "clip": true}, "extras": [{}, {}, {}, {}, {}, {}, {}, {}, {}, {}, {}, {}, {}, {}, {}, {}, {}, {}, {}, {}, {}, {}, {}, {}, {}, {}, {}, {}, {}, {}, {}, {}, {}, {}, {}, {}, {}, {}, {}, {}, {}, {}]}}